test/__init__.py
test/test_in_memory_readings_persistence.py
test/test_logger_factory.py
test/test_message_deque.py
test/test_mqtt_connectivity_service.py
test/test_os_file_management.py
test/test_os_firmware_update.py
test/test_wolk_connect.py
test/test_wolkabout_protocol_message_deserializer.py
test/test_wolkabout_protocol_message_factory.py
wolk/__init__.py
wolk/in_memory_readings_persistence.py
wolk/logger_factory.py
wolk/message_deque.py
wolk/mqtt_connectivity_service.py
wolk/os_file_management.py
wolk/os_firmware_update.py
wolk/wolk_connect.py
wolk/wolkabout_protocol_message_deserializer.py
wolk/wolkabout_protocol_message_factory.py
wolk/interface/__init__.py
wolk/interface/connectivity_service.py
wolk/interface/file_management.py
wolk/interface/firmware_handler.py
wolk/interface/firmware_update.py
wolk/interface/message_deserializer.py
wolk/interface/message_factory.py
wolk/interface/message_queue.py
wolk/interface/readings_persistence.py
wolk/model/__init__.py
wolk/model/data_delivery.py
wolk/model/data_type.py
wolk/model/device.py
wolk/model/feed_type.py
wolk/model/file_management_error_type.py
wolk/model/file_management_status.py
wolk/model/file_management_status_type.py
wolk/model/file_transfer_package.py
wolk/model/firmware_update_error_type.py
wolk/model/firmware_update_status.py
wolk/model/firmware_update_status_type.py
wolk/model/message.py
wolk/model/unit.py
wolk_connect-5.1.0.dist-info/LICENSE
wolk_connect-5.1.0.dist-info/METADATA
wolk_connect-5.1.0.dist-info/WHEEL
wolk_connect-5.1.0.dist-info/top_level.txt
wolk_connect-5.1.0.dist-info/RECORD
