Metadata-Version: 2.1
Name: wolk-connect
Version: 5.1.0
Summary: Python 3 library for connecting to WolkAbout IoT Platform
Home-page: https://github.com/Wolkabout/WolkConnect-Python
Author: WolkAbout
Author-email: info@wolkabout.com
License: Apache License 2.0
Keywords: IoT,WolkAbout,Internet of Things
Classifier: Development Status :: 5 - Production/Stable
Classifier: Intended Audience :: Developers
Classifier: License :: OSI Approved :: Apache Software License
Classifier: Natural Language :: English
Classifier: Programming Language :: Python :: 3 :: Only
Classifier: Programming Language :: Python :: 3.7
Classifier: Programming Language :: Python :: 3.8
Classifier: Operating System :: OS Independent
Classifier: Topic :: Internet
Classifier: Topic :: Communications
Classifier: Topic :: Software Development :: Embedded Systems
License-File: LICENSE
Requires-Dist: paho-mqtt (>=1.5.1)
Requires-Dist: requests (>=2.18.1)
